ebdataset/__init__.py
ebdataset/audio/__init__.py
ebdataset/audio/ntidigits.py
ebdataset/bci/ECoGJoystickTracking.py
ebdataset/bci/__init__.py
ebdataset/generated/__init__.py
ebdataset/generated/parity.py
ebdataset/utils/__init__.py
ebdataset/utils/units.py
ebdataset/vision/__init__.py
ebdataset/vision/ibm_gesture.py
ebdataset/vision/ini_roshambo.py
ebdataset/vision/ini_ucf50.py
ebdataset/vision/ncaltech101.py
ebdataset/vision/nmnist.py
ebdataset/vision/prophesee_ncars.py
ebdataset/vision/transforms.py
ebdataset/vision/type.py
ebdataset/vision/parsers/__init__.py
ebdataset/vision/parsers/aedat.py
ebdataset/vision/parsers/aer.py
ebdataset/vision/parsers/atis.py
ebdataset/visualization/__init__.py
ebdataset/visualization/spike_train_to_vid.py
ebdataset/visualization/time_binning.py
ebdataset-0.1.0.dist-info/LICENSE
ebdataset-0.1.0.dist-info/METADATA
ebdataset-0.1.0.dist-info/WHEEL
ebdataset-0.1.0.dist-info/top_level.txt
ebdataset-0.1.0.dist-info/RECORD
