Metadata-Version: 2.1
Name: ebdataset
Version: 0.1.0
Summary: An event based dataset loader under one common API.
Home-page: https://github.com/tihbe/python-ebdataset
Author: Ismael Balafrej - NECOTIS
Author-email: ismael.balafrej@usherbrooke.ca
License: UNKNOWN
Platform: UNKNOWN
Classifier: Development Status :: 3 - Alpha
Classifier: Programming Language :: Python :: 3 :: Only
Classifier: License :: OSI Approved :: MIT License
Classifier: Operating System :: OS Independent
Requires-Python: >=3.5.2
License-File: LICENSE
Requires-Dist: numpy (>=1.14.3)
Requires-Dist: pint (>=0.17)
Requires-Dist: tqdm (>=4.45.0)
Requires-Dist: torch (>=1.4.0)
Requires-Dist: torchvision (>=0.5.0)
Requires-Dist: h5py (>=2.10.0)
